.class public Life
.super java/lang/Object
.field private UNDERPOP_LIM I
.field private OVERPOP_LIM I
.field private REPRODUCE_NUM I
.field private LOOPS_PER_MS I
.field private xMax I
.field private yMax I
.field private 'field' [I

.method public <init>()V
        aload_0
        invokespecial java/lang/Object.<init>()V
        return
.end method

.method public static main([Ljava/lang/String;)V
        .limit stack 7
        .limit locals 7
        new Life
        dup
        astore 1
        aload 1
        invokespecial Life.<init>()V
        aload 1
        astore 3
        aload 3
        invokevirtual Life.init()Z
        iconst_1
        iconst_1
        if_icmpeq Body1
        goto EndLoop1
Body1:
        aload 3
        invokevirtual Life.printField()Z
        aload 3
        invokevirtual Life.update()Z
        invokestatic io.read()V
        goto Loop1
        return
.end method

.method public init()Z
        .limit stack 9
        .limit locals 19
        iconst_1
        newarray int
        astore 1
        aload_0
        iconst_2
        putfield Life/UNDERPOP_LIM I
        aload_0
        iconst_3
        putfield Life/OVERPOP_LIM I
        aload_0
        iconst_3
        putfield Life/REPRODUCE_NUM I
        aload_0
        ldc 225000
        putfield Life/LOOPS_PER_MS I
        aload_0
        aload 1
        invokevirtual Life.field([I)[I
        astore 7
        aload_0
        aload 7
        putfield Life/field [I
        iconst_0
        istore 9
        aload 1
        iload 9
        iaload
        istore 10
        iload 10
        iconst_1
        isub
        istore 11
        aload_0
        iload 11
        putfield Life/xMax I
        aload_0
        getfield Life/field [I
        astore 13
        aload 13
        arraylength
        istore 14
        iload 14
        iload 10
        idiv
        istore 15
        iload 15
        iconst_1
        isub
        istore 16
        aload_0
        iload 16
        putfield Life/yMax I
        iconst_1
        ireturn
.end method

.method public field([I)[I
        .limit stack 4
        .limit locals 108
        bipush 100
        newarray int
        astore 2
        aload_0
        iload 2
        putfield Life/field [I
        iconst_0
        istore 5
        aload 1
        iload 5
        bipush 10
        iastore
        iconst_0
        istore 6
        aload 4
        iload 6
        iconst_0
        iastore
        iconst_1
        istore 7
        aload 4
        iload 7
        iconst_0
        iastore
        iconst_2
        istore 8
        aload 4
        iload 8
        iconst_1
        iastore
        iconst_3
        istore 9
        aload 4
        iload 9
        iconst_0
        iastore
        iconst_4
        istore 10
        aload 4
        iload 10
        iconst_0
        iastore
        iconst_5
        istore 11
        aload 4
        iload 11
        iconst_0
        iastore
        bipush 6
        istore 12
        aload 4
        iload 12
        iconst_0
        iastore
        bipush 7
        istore 13
        aload 4
        iload 13
        iconst_0
        iastore
        bipush 8
        istore 14
        aload 4
        iload 14
        iconst_0
        iastore
        bipush 9
        istore 15
        aload 4
        iload 15
        iconst_0
        iastore
        bipush 10
        istore 16
        aload 4
        iload 16
        iconst_1
        iastore
        bipush 11
        istore 17
        aload 4
        iload 17
        iconst_0
        iastore
        bipush 12
        istore 18
        aload 4
        iload 18
        iconst_1
        iastore
        bipush 13
        istore 19
        aload 4
        iload 19
        iconst_0
        iastore
        bipush 14
        istore 20
        aload 4
        iload 20
        iconst_0
        iastore
        bipush 15
        istore 21
        aload 4
        iload 21
        iconst_0
        iastore
        bipush 16
        istore 22
        aload 4
        iload 22
        iconst_0
        iastore
        bipush 17
        istore 23
        aload 4
        iload 23
        iconst_0
        iastore
        bipush 18
        istore 24
        aload 4
        iload 24
        iconst_0
        iastore
        bipush 19
        istore 25
        aload 4
        iload 25
        iconst_0
        iastore
        bipush 20
        istore 26
        aload 4
        iload 26
        iconst_0
        iastore
        bipush 21
        istore 27
        aload 4
        iload 27
        iconst_1
        iastore
        bipush 22
        istore 28
        aload 4
        iload 28
        iconst_1
        iastore
        bipush 23
        istore 29
        aload 4
        iload 29
        iconst_0
        iastore
        bipush 24
        istore 30
        aload 4
        iload 30
        iconst_0
        iastore
        bipush 25
        istore 31
        aload 4
        iload 31
        iconst_0
        iastore
        bipush 26
        istore 32
        aload 4
        iload 32
        iconst_0
        iastore
        bipush 27
        istore 33
        aload 4
        iload 33
        iconst_0
        iastore
        bipush 28
        istore 34
        aload 4
        iload 34
        iconst_0
        iastore
        bipush 29
        istore 35
        aload 4
        iload 35
        iconst_0
        iastore
        bipush 30
        istore 36
        aload 4
        iload 36
        iconst_0
        iastore
        bipush 31
        istore 37
        aload 4
        iload 37
        iconst_0
        iastore
        bipush 32
        istore 38
        aload 4
        iload 38
        iconst_0
        iastore
        bipush 33
        istore 39
        aload 4
        iload 39
        iconst_0
        iastore
        bipush 34
        istore 40
        aload 4
        iload 40
        iconst_0
        iastore
        bipush 35
        istore 41
        aload 4
        iload 41
        iconst_0
        iastore
        bipush 36
        istore 42
        aload 4
        iload 42
        iconst_0
        iastore
        bipush 37
        istore 43
        aload 4
        iload 43
        iconst_0
        iastore
        bipush 38
        istore 44
        aload 4
        iload 44
        iconst_0
        iastore
        bipush 39
        istore 45
        aload 4
        iload 45
        iconst_0
        iastore
        bipush 40
        istore 46
        aload 4
        iload 46
        iconst_0
        iastore
        bipush 41
        istore 47
        aload 4
        iload 47
        iconst_0
        iastore
        bipush 42
        istore 48
        aload 4
        iload 48
        iconst_0
        iastore
        bipush 43
        istore 49
        aload 4
        iload 49
        iconst_0
        iastore
        bipush 44
        istore 50
        aload 4
        iload 50
        iconst_0
        iastore
        bipush 45
        istore 51
        aload 4
        iload 51
        iconst_0
        iastore
        bipush 46
        istore 52
        aload 4
        iload 52
        iconst_0
        iastore
        bipush 47
        istore 53
        aload 4
        iload 53
        iconst_0
        iastore
        bipush 48
        istore 54
        aload 4
        iload 54
        iconst_0
        iastore
        bipush 49
        istore 55
        aload 4
        iload 55
        iconst_0
        iastore
        bipush 50
        istore 56
        aload 4
        iload 56
        iconst_0
        iastore
        bipush 51
        istore 57
        aload 4
        iload 57
        iconst_0
        iastore
        bipush 52
        istore 58
        aload 4
        iload 58
        iconst_0
        iastore
        bipush 53
        istore 59
        aload 4
        iload 59
        iconst_0
        iastore
        bipush 54
        istore 60
        aload 4
        iload 60
        iconst_0
        iastore
        bipush 55
        istore 61
        aload 4
        iload 61
        iconst_0
        iastore
        bipush 56
        istore 62
        aload 4
        iload 62
        iconst_0
        iastore
        bipush 57
        istore 63
        aload 4
        iload 63
        iconst_0
        iastore
        bipush 58
        istore 64
        aload 4
        iload 64
        iconst_0
        iastore
        bipush 59
        istore 65
        aload 4
        iload 65
        iconst_0
        iastore
        bipush 60
        istore 66
        aload 4
        iload 66
        iconst_0
        iastore
        bipush 61
        istore 67
        aload 4
        iload 67
        iconst_0
        iastore
        bipush 62
        istore 68
        aload 4
        iload 68
        iconst_0
        iastore
        bipush 63
        istore 69
        aload 4
        iload 69
        iconst_0
        iastore
        bipush 64
        istore 70
        aload 4
        iload 70
        iconst_0
        iastore
        bipush 65
        istore 71
        aload 4
        iload 71
        iconst_0
        iastore
        bipush 66
        istore 72
        aload 4
        iload 72
        iconst_0
        iastore
        bipush 67
        istore 73
        aload 4
        iload 73
        iconst_0
        iastore
        bipush 68
        istore 74
        aload 4
        iload 74
        iconst_0
        iastore
        bipush 69
        istore 75
        aload 4
        iload 75
        iconst_0
        iastore
        bipush 70
        istore 76
        aload 4
        iload 76
        iconst_0
        iastore
        bipush 71
        istore 77
        aload 4
        iload 77
        iconst_0
        iastore
        bipush 72
        istore 78
        aload 4
        iload 78
        iconst_0
        iastore
        bipush 73
        istore 79
        aload 4
        iload 79
        iconst_0
        iastore
        bipush 74
        istore 80
        aload 4
        iload 80
        iconst_0
        iastore
        bipush 75
        istore 81
        aload 4
        iload 81
        iconst_0
        iastore
        bipush 76
        istore 82
        aload 4
        iload 82
        iconst_0
        iastore
        bipush 77
        istore 83
        aload 4
        iload 83
        iconst_0
        iastore
        bipush 78
        istore 84
        aload 4
        iload 84
        iconst_0
        iastore
        bipush 79
        istore 85
        aload 4
        iload 85
        iconst_0
        iastore
        bipush 80
        istore 86
        aload 4
        iload 86
        iconst_0
        iastore
        bipush 81
        istore 87
        aload 4
        iload 87
        iconst_0
        iastore
        bipush 82
        istore 88
        aload 4
        iload 88
        iconst_0
        iastore
        bipush 83
        istore 89
        aload 4
        iload 89
        iconst_0
        iastore
        bipush 84
        istore 90
        aload 4
        iload 90
        iconst_0
        iastore
        bipush 85
        istore 91
        aload 4
        iload 91
        iconst_0
        iastore
        bipush 86
        istore 92
        aload 4
        iload 92
        iconst_0
        iastore
        bipush 87
        istore 93
        aload 4
        iload 93
        iconst_0
        iastore
        bipush 88
        istore 94
        aload 4
        iload 94
        iconst_0
        iastore
        bipush 89
        istore 95
        aload 4
        iload 95
        iconst_0
        iastore
        bipush 90
        istore 96
        aload 4
        iload 96
        iconst_0
        iastore
        bipush 91
        istore 97
        aload 4
        iload 97
        iconst_0
        iastore
        bipush 92
        istore 98
        aload 4
        iload 98
        iconst_0
        iastore
        bipush 93
        istore 99
        aload 4
        iload 99
        iconst_0
        iastore
        bipush 94
        istore 100
        aload 4
        iload 100
        iconst_0
        iastore
        bipush 95
        istore 101
        aload 4
        iload 101
        iconst_0
        iastore
        bipush 96
        istore 102
        aload 4
        iload 102
        iconst_0
        iastore
        bipush 97
        istore 103
        aload 4
        iload 103
        iconst_0
        iastore
        bipush 98
        istore 104
        aload 4
        iload 104
        iconst_0
        iastore
        bipush 99
        istore 105
        aload 4
        iload 105
        iconst_0
        iastore
        aload_0
        getfield Life/field [I
        astore 106
        aload 106
        areturn
.end method

.method public update()Z
        .limit stack 15
        .limit locals 26
        aload_0
        getfield Life/field [I
        astore 1
        aload 1
        arraylength
        istore 3
iload 3
        newarray int
        astore 4
        iconst_0
        istore 6
Loop2:
        aload_0
        getfield Life/field [I
        astore 7
        aload 7
        arraylength
        istore 8
        iload 6
        iload 8
        if_icmplt Body2
        goto EndLoop2
Body2:
        iload 6
        istore 9
        aload 2
        iload 9
        iaload
        istore 10
        aload_0
        iload 6
        invokevirtual Life.getLiveNeighborN(I)I
        istore 11
        iload 10
        iconst_1
        ilth
        istore 12
        iload 12
        iload 12
        if_icmp_not_dealed ifBlock1
        aload_0
        getfield Life/REPRODUCE_NUM I
        istore 13
        aload_0
        iload 11
        iload 13
        invokevirtual Life.eq(II)Z
        istore 15
        aload 15
        iconst_1
        if_icmpeq ifBlock2
        iload 6
        istore 16
        aload 4
        iload 6
        aload 2
        iload 16
        iaload
        iastore
        goto endif2
ifBlock2:
        aload 4
        iload 6
        iconst_1
        iastore
        goto endif1
ifBlock1:
        aload_0
        getfield Life/UNDERPOP_LIM I
        istore 17
        aload_0
        iload 11
        iload 17
        invokevirtual Life.ge(II)Z
        istore 19
        aload_0
        getfield Life/OVERPOP_LIM I
        istore 20
        aload_0
        iload 11
        iload 20
        invokevirtual Life.le(II)Z
        istore 22
        iload 19
        iload 22
        iand
        istore 23
        iload 23
        iload 23
        if_icmp_not_dealed ifBlock3
        iload 6
        istore 24
        aload 4
        iload 6
        aload 2
        iload 24
        iaload
        iastore
        goto endif3
ifBlock3:
        aload 4
        iload 6
        iconst_0
        iastore
endif3:
endif1:
        iload 6
        iconst_1
        iadd
        istore 6
        goto Loop2
EndLoop2:
        aload_0
        aload 4
        putfield Life/field [I
        iconst_1
        ireturn
.end method

.method public printField()Z
        .limit stack 5
        .limit locals 13
        iconst_0
        istore 1
        iconst_0
        istore 2
Loop3:
        aload_0
        getfield Life/field [I
        astore 3
        aload 3
        arraylength
        istore 5
        iload 1
        iload 5
        if_icmplt Body3
        goto EndLoop3
Body3:
        aload_0
        getfield Life/xMax I
        istore 6
        aload_0
        iload 2
        iload 6
        invokevirtual Life.gt(II)Z
        istore 8
        aload 8
        iconst_1
        if_icmpeq ifBlock4
        goto endif4
ifBlock4:
        invokestatic io.println()V
        iconst_0
        istore 2
endif4:
        iload 1
        istore 10
        aload 4
        iload 10
        iaload
        istore 11
        iload 11
        invokestatic io.print(I)V
        iload 1
        iconst_1
        iadd
        istore 1
        iload 2
        iconst_1
        iadd
        istore 2
        goto Loop3
EndLoop3:
        invokestatic io.println()V
        invokestatic io.println()V
        iconst_1
        ireturn
.end method

.method public trIdx(II)I
        .limit stack 3
        .limit locals 9
        aload_0
        getfield Life/xMax I
        istore 3
        iload 3
        iconst_1
        iadd
        istore 5
        iload 5
        iload 2
        imul
        istore 6
        iload 1
        iload 6
        iadd
        istore 7
        iload 7
        ireturn
.end method

.method public cartIdx(I)[I
        .limit stack 4
        .limit locals 13
        aload_0
        getfield Life/xMax I
        istore 2
        iload 2
        iconst_1
        iadd
        istore 4
        iload 1
        iload 4
        idiv
        istore 5
        iload 5
        iload 4
        imul
        istore 6
        iload 1
        iload 6
        isub
        istore 7
        iconst_2
        newarray int
        astore 8
        iconst_0
        istore 10
        aload 8
        iload 10
        iload 7
        iastore
        iconst_1
        istore 11
        aload 8
        iload 11
        iload 5
        iastore
        aload 8
        areturn
.end method

.method public getNeighborCoords(I)[I
        .limit stack 19
        .limit locals 30
        aload_0
        iload 1
        invokevirtual Life.cartIdx(I)[I
        astore 2
        iconst_0
        istore 3
        aload 2
        iload 3
        iaload
        istore 4
        iconst_1
        istore 5
        aload 2
        iload 5
        iaload
        istore 6
        aload_0
        getfield Life/xMax I
        istore 7
        iload 4
        iload 7
        if_icmplt ifBlock5
        iconst_0
        istore 9
        iload 4
        iconst_1
        isub
        istore 10
        goto endif5
ifBlock5:
        iload 4
        iconst_1
        iadd
        istore 9
        aload_0
        iload 4
        iconst_0
        invokevirtual Life.gt(II)Z
        istore 11
        aload 11
        iconst_1
        if_icmpeq ifBlock6
        aload_0
        getfield Life/xMax I
        istore 12
        iload 12
        istore 10
        goto endif6
ifBlock6:
        iload 4
        iconst_1
        isub
        istore 10
endif6:
endif5:
        aload_0
        getfield Life/yMax I
        istore 13
        iload 6
        iload 13
        if_icmplt ifBlock7
        iconst_0
        istore 15
        iload 6
        iconst_1
        isub
        istore 16
        goto endif7
ifBlock7:
        iload 6
        iconst_1
        iadd
        istore 15
        aload_0
        iload 6
        iconst_0
        invokevirtual Life.gt(II)Z
        istore 17
        aload 17
        iconst_1
        if_icmpeq ifBlock8
        aload_0
        getfield Life/yMax I
        istore 18
        iload 18
        istore 16
        goto endif8
ifBlock8:
        iload 6
        iconst_1
        isub
        istore 16
endif8:
endif7:
        bipush 8
        newarray int
        astore 19
        iconst_0
        istore 21
        aload 19
        iload 21
        aload_0
        iload 4
        iload 16
        invokevirtual Life.trIdx(II)I
        iastore
        iconst_1
        istore 22
        aload 19
        iload 22
        aload_0
        iload 10
        iload 16
        invokevirtual Life.trIdx(II)I
        iastore
        iconst_2
        istore 23
        aload 19
        iload 23
        aload_0
        iload 10
        iload 6
        invokevirtual Life.trIdx(II)I
        iastore
        iconst_3
        istore 24
        aload 19
        iload 24
        aload_0
        iload 10
        iload 15
        invokevirtual Life.trIdx(II)I
        iastore
        iconst_4
        istore 25
        aload 19
        iload 25
        aload_0
        iload 4
        iload 15
        invokevirtual Life.trIdx(II)I
        iastore
        iconst_5
        istore 26
        aload 19
        iload 26
        aload_0
        iload 9
        iload 15
        invokevirtual Life.trIdx(II)I
        iastore
        bipush 6
        istore 27
        aload 19
        iload 27
        aload_0
        iload 9
        iload 6
        invokevirtual Life.trIdx(II)I
        iastore
        bipush 7
        istore 28
        aload 19
        iload 28
        aload_0
        iload 9
        iload 16
        invokevirtual Life.trIdx(II)I
        iastore
        aload 19
        areturn
.end method

.method public getLiveNeighborN(I)I
        .limit stack 5
        .limit locals 12
        iconst_0
        istore 2
        aload_0
        iload 1
        invokevirtual Life.getNeighborCoords(I)[I
        astore 3
        iconst_0
        istore 4
Loop4:
        aload 3
        arraylength
        istore 5
        iload 4
        iload 5
        if_icmplt Body4
        goto EndLoop4
Body4:
        iload 4
        istore 6
        aload 3
        iload 6
        iaload
        istore 7
        aload 9
        iload 7
        istore 8
        aload_0
        iload 8
        iconst_0
        invokevirtual Life.ne(II)Z
        istore 10
        aload 10
        iconst_1
        if_icmpeq ifBlock9
        goto endif9
ifBlock9:
        iload 2
        iconst_1
        iadd
        istore 2
endif9:
        iload 4
        iconst_1
        iadd
        istore 4
        goto Loop4
EndLoop4:
        iload 2
        ireturn
.end method

.method public busyWait(I)Z
        .limit stack 3
        .limit locals 7
        aload_0
        getfield Life/LOOPS_PER_MS I
        istore 2
        iload 1
        iload 2
        imul
        istore 4
        iconst_0
        istore 5
        iload 5
        iload 4
        if_icmplt Body5
        goto EndLoop5
Body5:
        iload 5
        iconst_1
        iadd
        istore 5
        goto Loop5
EndLoop5:
        iconst_1
        ireturn
.end method

.method public eq(II)Z
        .limit stack 4
        .limit locals 9
        aload_0
        iload 1
        iload 2
        invokevirtual Life.lt(II)Z
        istore 3
        iload 3
        istore 4
        aload_0
        iload 2
        iload 1
        invokevirtual Life.lt(II)Z
        istore 5
        iload 5
        istore 6
        iload 4
        iload 6
        iand
        istore 7
        iload 7
        ireturn
.end method

.method public ne(II)Z
        .limit stack 3
        .limit locals 6
        aload_0
        iload 1
        iload 2
        invokevirtual Life.eq(II)Z
        istore 3
        iload 3
        istore 4
        iload 4
        ireturn
.end method

.method public lt(II)Z
        .limit stack 2
        .limit locals 4
        iload 1
        iload 2
        ilth
        istore 3
        iload 3
        ireturn
.end method

.method public le(II)Z
        .limit stack 4
        .limit locals 10
        aload_0
        iload 1
        iload 2
        invokevirtual Life.lt(II)Z
        istore 3
        iload 3
        istore 4
        aload_0
        iload 1
        iload 2
        invokevirtual Life.eq(II)Z
        istore 5
        iload 5
        istore 6
        iload 4
        iload 6
        iand
        istore 7
        iload 7
        istore 8
        iload 8
        ireturn
.end method

.method public gt(II)Z
        .limit stack 3
        .limit locals 6
        aload_0
        iload 1
        iload 2
        invokevirtual Life.le(II)Z
        istore 3
        iload 3
        istore 4
        iload 4
        ireturn
.end method

.method public ge(II)Z
        .limit stack 4
        .limit locals 10
        aload_0
        iload 1
        iload 2
        invokevirtual Life.gt(II)Z
        istore 3
        iload 3
        istore 4
        aload_0
        iload 1
        iload 2
        invokevirtual Life.eq(II)Z
        istore 5
        iload 5
        istore 6
        iload 4
        iload 6
        iand
        istore 7
        iload 7
        istore 8
        iload 8
        ireturn
.end method
